run_configurations.py
run_configurations-1.1.1.dist-info/METADATA
run_configurations-1.1.1.dist-info/WHEEL
run_configurations-1.1.1.dist-info/entry_points.txt
run_configurations-1.1.1.dist-info/top_level.txt
run_configurations-1.1.1.dist-info/RECORD
