Metadata-Version: 2.2
Name: run_configurations
Version: 1.1.1
Summary: A small script that allows quickly executing run configurations from the command line including shell completions 
Home-page: https://github.com/bvolkmer/run_configurations
Author: Benedikt Volkmer
License: MIT
Requires-Python: >=3.8
Requires-Dist: click
Requires-Dist: levenshtein
Dynamic: author
Dynamic: description
Dynamic: description-content-type
Dynamic: home-page
Dynamic: license
Dynamic: requires-dist
Dynamic: requires-python
Dynamic: summary
